serene/__init__.py
serene-0.0.2.dist-info/METADATA
serene-0.0.2.dist-info/WHEEL
serene-0.0.2.dist-info/RECORD
