Metadata-Version: 2.4
Name: serene
Version: 0.0.2
Summary: A Python package that provides flirty messages
Author-email: Shreya Subramanya <shreya.shweta@gmail.com>
Classifier: Programming Language :: Python :: 3
Classifier: Programming Language :: Python :: 3.9
Classifier: Programming Language :: Python :: 3.10
Classifier: Programming Language :: Python :: 3.11
Classifier: Programming Language :: Python :: 3.12
Classifier: Programming Language :: Python :: 3.13
Requires-Python: <4.0,>=3.9
